FinanceAgent/__init__.py
FinanceAgent/base.py
FinanceAgent/stock/__init__.py
FinanceAgent/stock/data_util_py3.py
FinanceAgent/stock/request_constants.py
FinanceAgent/stock/request_stock_price_india_nse.py
financeagent_india-0.2.1.dist-info/METADATA
financeagent_india-0.2.1.dist-info/WHEEL
financeagent_india-0.2.1.dist-info/top_level.txt
financeagent_india-0.2.1.dist-info/RECORD
