Metadata-Version: 2.4
Name: financeagent-india
Version: 0.2.1
Summary: Lightweight India NSE stock quotes (MoneyControl) - pruned & optimized.
Author: FinanceAgent Contributors
Author-email: arushsinghal98@gmail.com
Project-URL: Homepage, https://pypi.org/project/financeagent-india/
Keywords: finance stock nse india moneycontrol quotes
Classifier: Development Status :: 3 - Alpha
Classifier: Intended Audience :: Developers
Classifier: Topic :: Software Development :: Build Tools
Classifier: License :: OSI Approved :: MIT License
Requires-Python: >=3.4
Requires-Dist: requests>=2.25.0
Requires-Dist: beautifulsoup4>=4.9.0
Dynamic: author
Dynamic: author-email
Dynamic: classifier
Dynamic: description
Dynamic: description-content-type
Dynamic: keywords
Dynamic: project-url
Dynamic: requires-dist
Dynamic: requires-python
Dynamic: summary
